imputegap/__init__.py
imputegap/hereliande.py
imputegap/runner_benchmark.py
imputegap/runner_cleaner.py
imputegap/runner_contamination.py
imputegap/runner_display.py
imputegap/runner_downstream.py
imputegap/runner_efeatures.py
imputegap/runner_explainer.py
imputegap/runner_imputation.py
imputegap/runner_loading.py
imputegap/runner_optimization.py
imputegap/runner_validation.py
imputegap/script_180.py
imputegap/script_181.py
imputegap/script_182.py
imputegap/script_lan.py
imputegap/z_runner_validation.py
imputegap/algorithms/__init__.py
imputegap/algorithms/bayotide.py
imputegap/algorithms/bit_graph.py
imputegap/algorithms/brits.py
imputegap/algorithms/cdrec.py
imputegap/algorithms/cpp_integration.py
imputegap/algorithms/csdi.py
imputegap/algorithms/deep_mvi.py
imputegap/algorithms/dynammo.py
imputegap/algorithms/gain.py
imputegap/algorithms/gpt4ts.py
imputegap/algorithms/grin.py
imputegap/algorithms/grouse.py
imputegap/algorithms/hkmf_t.py
imputegap/algorithms/iim.py
imputegap/algorithms/interpolation.py
imputegap/algorithms/iterative_svd.py
imputegap/algorithms/knn.py
imputegap/algorithms/mean_impute.py
imputegap/algorithms/mean_impute_by_series.py
imputegap/algorithms/mice.py
imputegap/algorithms/min_impute.py
imputegap/algorithms/miss_forest.py
imputegap/algorithms/miss_net.py
imputegap/algorithms/mpin.py
imputegap/algorithms/mrnn.py
imputegap/algorithms/nuwats.py
imputegap/algorithms/pristi.py
imputegap/algorithms/rosl.py
imputegap/algorithms/saits.py
imputegap/algorithms/soft_impute.py
imputegap/algorithms/spirit.py
imputegap/algorithms/stmvl.py
imputegap/algorithms/svt.py
imputegap/algorithms/test.py
imputegap/algorithms/timesnet.py
imputegap/algorithms/tkcm.py
imputegap/algorithms/trmf.py
imputegap/algorithms/xgboost.py
imputegap/algorithms/zero_impute.py
imputegap/algorithms/lib/lib_algo.dll
imputegap/algorithms/lib/lib_algo.so
imputegap/algorithms/lib/lib_cdrec.dylib
imputegap/algorithms/lib/lib_cdrec.so
imputegap/algorithms/lib/lib_cdrec_new.dylib
imputegap-1.1.2.dist-info/licenses/LICENSE.txt
imputegap-1.1.2.dist-info/METADATA
imputegap-1.1.2.dist-info/WHEEL
imputegap-1.1.2.dist-info/entry_points.txt
imputegap-1.1.2.dist-info/top_level.txt
imputegap-1.1.2.dist-info/RECORD
