Metadata-Version: 2.4
Name: imputegap
Version: 1.1.2
Summary: A Library of Imputation Techniques for Time Series Data
Home-page: https://github.com/eXascaleInfolab/ImputeGAP
Author: Quentin Nater
Author-email: quentin.nater@unifr.ch
License: MIT License
Project-URL: Documentation, https://imputegap.readthedocs.io/
Project-URL: Source, https://github.com/eXascaleInfolab/ImputeGAP
Classifier: Development Status :: 3 - Alpha
Classifier: Intended Audience :: Developers
Classifier: Programming Language :: Python :: 3.12
Classifier: Topic :: Scientific/Engineering :: Information Analysis
Classifier: License :: OSI Approved :: MIT License
Requires-Python: >=3.11
License-File: LICENSE.txt
Requires-Dist: matplotlib>=3.7.5
Requires-Dist: toml>=0.10.2
Requires-Dist: scikit-learn>=1.5.0
Requires-Dist: scipy>=1.14.1
Requires-Dist: tensorflow>=2.16.2
Requires-Dist: numpy>=2.3.5
Requires-Dist: shap>=0.44.1
Requires-Dist: scikit-optimize>=0.10.2
Requires-Dist: pyswarms>=1.3.0
Requires-Dist: pytest>=8.3.3
Requires-Dist: xlsxwriter>=3.2.0
Requires-Dist: types-toml
Requires-Dist: types-setuptools
Requires-Dist: wheel
Requires-Dist: sktime>=0.35.0
Requires-Dist: statsmodels>=0.14.4
Requires-Dist: prophet>=1.1.6
Requires-Dist: plotly>=5.24.1
Requires-Dist: darts>=0.34.0
Requires-Dist: torch>=2.5.1
Requires-Dist: torchvision>=0.20.1
Requires-Dist: torchaudio>=2.5.1
Requires-Dist: ujson>=5.10.0
Requires-Dist: ipdb>=0.13.13
Requires-Dist: pandas>=2.0.3
Requires-Dist: torchcde>=0.2.5
Requires-Dist: tables>=3.10.1
Requires-Dist: MissForest>=4.2.3
Requires-Dist: lightgbm>=4.6.0
Requires-Dist: xgboost>=2.1.4
Requires-Dist: tsfel>=0.1.9
Requires-Dist: tsfresh>=0.20.3
Requires-Dist: einops>=0.8.0
Requires-Dist: ray>=2.41.0
Requires-Dist: ray[tune]>=2.41.0
Requires-Dist: fire>=0.7.0
Requires-Dist: fastdtw>=0.3.4
Requires-Dist: torch-geometric>=2.6.1
Requires-Dist: pytorch-lightning>=2.5.0
Requires-Dist: torchmetrics>=1.6.1
Requires-Dist: lightning>=2.5.0
Requires-Dist: pycatch22>=0.4.5
Requires-Dist: reformer-pytorch>=1.4.4
Requires-Dist: transformers>=4.52.4
Requires-Dist: timm>=1.0.15
Requires-Dist: pyqt5>=5.15.11
Requires-Dist: tsdb>=0.7.1
Requires-Dist: linear-attention-transformer>=0.19.1
Requires-Dist: pmdarima>=2.1.1
Requires-Dist: statsforecast>=1.0.0
Dynamic: author
Dynamic: author-email
Dynamic: classifier
Dynamic: description
Dynamic: description-content-type
Dynamic: home-page
Dynamic: license
Dynamic: license-file
Dynamic: project-url
Dynamic: requires-dist
Dynamic: requires-python
Dynamic: summary
